Encoder8_3/encoder83.v
module encoder83(
    input d0,d1,d2,d3,d4,d5,d6,d7,
    output [2:0] y
);

    assign y[0] = d1 | d3 | d5 | d7;
    assign y[1] = d2 | d3 | d6 | d7;
    assign y[2] = d4 | d5 | d6 | d7;

endmodule

Encoder8_3/tb_encoder83.v
`include "encoder83.v"
`timescale 1ns/1ps

module tb_encoder83;
    reg d1,d2,d3,d4,d5,d6,d7,d0;
    wire [2:0] y;

    encoder83 uut(
        .d0(d0),
        .d1(d1),
        .d2(d2),
        .d3(d3),
        .d4(d4),
        .d5(d5),
        .d6(d6),
        .d7(d7),
        .y(y)
    );
  // Lặp qua từng bit từ d0 đến d7
    integer i;
    initial begin
        $dumpfile("tb_encoder83.vcd");
        $dumpvars(0,tb_encoder83);
    end

     initial begin
    $display("Time | d7 d6 d5 d4 d3 d2 d1 d0 | y");
    $display("-----|------------------------|---");

  
    for (i = 0; i < 8; i = i + 1) begin
      {d7, d6, d5, d4, d3, d2, d1, d0} = 8'b00000000;
      case (i)
        0: d0 = 1;
        1: d1 = 1;
        2: d2 = 1;
        3: d3 = 1;
        4: d4 = 1;
        5: d5 = 1;
        6: d6 = 1;
        7: d7 = 1;
      endcase

      #10; // Chờ một chút để tín hiệu ổn định
      $display("%4t |  %b  | %b", $time, {d7,d6,d5,d4,d3,d2,d1,d0}, y);
    end

    $finish;
  end

endmodule

Encoder8_3/tb_encoder83.vcd
$date
	Sun Jul 13 06:48:17 2025
$end
$version
	Icarus Verilog
$end
$timescale
	1ps
$end
$scope module tb_encoder83 $end
$var wire 3 ! y [2:0] $end
$var reg 1 " d0 $end
$var reg 1 # d1 $end
$var reg 1 $ d2 $end
$var reg 1 % d3 $end
$var reg 1 & d4 $end
$var reg 1 ' d5 $end
$var reg 1 ( d6 $end
$var reg 1 ) d7 $end
$var integer 32 * i [31:0] $end
$scope module uut $end
$var wire 1 " d0 $end
$var wire 1 # d1 $end
$var wire 1 $ d2 $end
$var wire 1 % d3 $end
$var wire 1 & d4 $end
$var wire 1 ' d5 $end
$var wire 1 ( d6 $end
$var wire 1 ) d7 $end
$var wire 3 + y [2:0] $end
$upscope $end
$upscope $end
$enddefinitions $end
$comment Show the parameter values. $end
$dumpall
$end
#0
$dumpvars
b0 +
b0 *
0)
0(
0'
0&
0%
0$
0#
1"
b0 !
$end
#10000
b1 !
b1 +
1#
0"
b1 *
#20000
b10 !
b10 +
1$
0#
b10 *
#30000
b11 !
b11 +
1%
0$
b11 *
#40000
b100 !
b100 +
1&
0%
b100 *
#50000
b101 !
b101 +
1'
0&
b101 *
#60000
b110 !
b110 +
1(
0'
b110 *
#70000
b111 !
b111 +
1)
0(
b111 *
#80000
b1000 *
