FullAdder/full_adder.v
module full_adder(
    input a,
    input b,
    input c_in,
    output s,
    output c_out
);
    assign s = a^b^c_in;
    assign c_out = (a&b) | (b&c_in) | (a&c_in);

endmodule

FullAdder/tb_full_adder.v
`include "full_adder.v"
`timescale 1ns/1ps
module tb_full_adder;

    reg a, b, c_in;       // inputs điều khiển
    wire s, c_out;        // outputs từ full_adder

    // Instantiate the full adder module
    full_adder uut (
        .a(a),
        .b(b),
        .c_in(c_in),
        .s(s),
        .c_out(c_out)
    );

    // Dump waveform file
    initial begin
        $dumpfile("tb_full_adder.vcd");
        $dumpvars(0, tb_full_adder);

        // Test all combinations of 3 inputs (a, b, c_in)
        a = 0; b = 0; c_in = 0; #10;
        a = 0; b = 0; c_in = 1; #10;
        a = 0; b = 1; c_in = 0; #10;
        a = 0; b = 1; c_in = 1; #10;
        a = 1; b = 0; c_in = 0; #10;
        a = 1; b = 0; c_in = 1; #10;
        a = 1; b = 1; c_in = 0; #10;
        a = 1; b = 1; c_in = 1; #10;

        // Kết thúc mô phỏng
        $finish;
    end

endmodule

FullAdder/tb_full_adder.vcd
$date
	Wed Jul 09 08:13:35 2025
$end
$version
	Icarus Verilog
$end
$timescale
	1ps
$end
$scope module tb_full_adder $end
$var wire 1 ! s $end
$var wire 1 " c_out $end
$var reg 1 # a $end
$var reg 1 $ b $end
$var reg 1 % c_in $end
$scope module uut $end
$var wire 1 # a $end
$var wire 1 $ b $end
$var wire 1 % c_in $end
$var wire 1 " c_out $end
$var wire 1 ! s $end
$upscope $end
$upscope $end
$enddefinitions $end
$comment Show the parameter values. $end
$dumpall
$end
#0
$dumpvars
0%
0$
0#
0"
0!
$end
#10000
1!
1%
#20000
0%
1$
#30000
1"
0!
1%
#40000
0"
1!
0%
0$
1#
#50000
1"
0!
1%
#60000
0%
1$
#70000
1!
1%
