EvenDecoder/even_decoder.v
module even_decoder(
    input wire [3:0] a,
    output y
);

    assign y = a[0] ^ 1'b1;
    
endmodule

EvenDecoder/tb_even_decoder.v
`timescale 1ns/1ps
`include "even_decoder.v"

module tb_even_decoder;

    reg [3:0] a;
    wire y;

    even_decoder uut (
        .a(a),
        .y(y)
    );

    initial begin
        $dumpfile("tb_even_decoder.vcd");
        $dumpvars(0,tb_even_decoder);
    end

    integer i;

      initial begin
        $display("Time |  a  | y (Even?)");
        $display("----------------------");

        for (i = 0; i < 16; i = i + 1) begin
            a = i;                // đưa giá trị vào
            #10;                  // delay để ổn định
            $display("%4t | %2d |    %b", $time, a, y);
        end

        $finish;
    end

endmodule

EvenDecoder/tb_even_decoder.vcd
$date
	Thu Jul 10 08:40:46 2025
$end
$version
	Icarus Verilog
$end
$timescale
	1ps
$end
$scope module tb_even_decoder $end
$var wire 1 ! y $end
$var reg 4 " a [3:0] $end
$var integer 32 # i [31:0] $end
$scope module uut $end
$var wire 4 $ a [3:0] $end
$var wire 1 ! y $end
$upscope $end
$upscope $end
$enddefinitions $end
$comment Show the parameter values. $end
$dumpall
$end
#0
$dumpvars
b0 $
b0 #
b0 "
1!
$end
#10000
0!
b1 "
b1 $
b1 #
#20000
1!
b10 "
b10 $
b10 #
#30000
0!
b11 "
b11 $
b11 #
#40000
1!
b100 "
b100 $
b100 #
#50000
0!
b101 "
b101 $
b101 #
#60000
1!
b110 "
b110 $
b110 #
#70000
0!
b111 "
b111 $
b111 #
#80000
1!
b1000 "
b1000 $
b1000 #
#90000
0!
b1001 "
b1001 $
b1001 #
#100000
1!
b1010 "
b1010 $
b1010 #
#110000
0!
b1011 "
b1011 $
b1011 #
#120000
1!
b1100 "
b1100 $
b1100 #
#130000
0!
b1101 "
b1101 $
b1101 #
#140000
1!
b1110 "
b1110 $
b1110 #
#150000
0!
b1111 "
b1111 $
b1111 #
#160000
b10000 #
