Mux_4_1/mux4_1.v
module mux4_1(
    input  wire [1:0] sel,
    input  wire d0, d1, d2, d3,
    output wire y
);

    wire [3:0] temp_y;
    wire sel_val_3, sel_val_2, sel_val_1, sel_val_0;
    wire y2, y1;

    // Chọn d3: khi sel == 11 → sel_val_3 = sel[1] & sel[0]
    assign sel_val_3 = sel[1] & sel[0];
    assign temp_y[3] = d3 & sel_val_3;

    // Chọn giữa temp_y[3] và d2 (khi sel == 10)
    assign sel_val_2 = sel[1] & ~sel[0];
    mux2_1 mux_d2 (
        .a(temp_y[3]),
        .b(d2),
        .sel(sel_val_2),
        .y(temp_y[2])
    );

    // Chọn giữa temp_y[2] và d1 (khi sel == 01)
    assign sel_val_1 = ~sel[1] & sel[0];
    mux2_1 mux_d1 (
        .a(temp_y[2]),
        .b(d1),
        .sel(sel_val_1),
        .y(temp_y[1])
    );

    // Chọn giữa temp_y[1] và d0 (khi sel == 00)
    assign sel_val_0 = ~sel[1] & ~sel[0];
    mux2_1 mux_d0 (
        .a(temp_y[1]),
        .b(d0),
        .sel(sel_val_0),
        .y(temp_y[0])
    );

    assign y = temp_y[0];

endmodule


module mux2_1(
    input  wire a,
    input  wire b,
    input  wire sel,
    output wire y
);
    assign y = (a & ~sel) | (b & sel);
endmodule

Mux_4_1/tb_mux4_1.v
`timescale 1ns / 1ps
`include "mux4_1.v"
module tb_mux4_1;

    // Testbench signals
    reg [1:0] sel;
    reg d0, d1, d2, d3;
    wire y;

    // Instantiate DUT
    mux4_1 dut (
        .sel(sel),
        .d0(d0),
        .d1(d1),
        .d2(d2),
        .d3(d3),
        .y(y)
    );

    integer i;

    initial begin
        $dumpfile("tb_mux4_1.vcd");
        $dumpvars(0, tb_mux4_1);

        $display("=== Test Tất cả tổ hợp sel & dữ liệu ===");
        $display("sel | d0 d1 d2 d3 | y | Ghi chú");

        // Duyệt qua tất cả giá trị sel từ 00 đến 11
        for (i = 0; i < 4; i = i + 1) begin
            sel = i[1:0];
            
            // TH1: chỉ một đầu vào đúng
            d0 = 0; d1 = 0; d2 = 0; d3 = 0;
            case (sel)
                2'b00: d0 = 1;
                2'b01: d1 = 1;
                2'b10: d2 = 1;
                2'b11: d3 = 1;
            endcase
            #10;
            $display("%b   |  %b  %b  %b  %b | %b | Chọn đúng d%0d", sel, d0, d1, d2, d3, y, sel);

            // TH2: tất cả đều là 1
            d0 = 1; d1 = 1; d2 = 1; d3 = 1;
            #10;
            $display("%b   |  %b  %b  %b  %b | %b | Tất cả đầu vào là 1", sel, d0, d1, d2, d3, y);

            // TH3: đầu vào ngẫu nhiên
            d0 = $random % 2;
            d1 = $random % 2;
            d2 = $random % 2;
            d3 = $random % 2;
            #10;
            $display("%b   |  %b  %b  %b  %b | %b | Ngẫu nhiên", sel, d0, d1, d2, d3, y);
        end

        $display("=== Kết thúc kiểm thử ===");
        $finish;
    end

endmodule

Mux_4_1/tb_mux4_1.vcd
$date
	Wed Jul 09 11:10:32 2025
$end
$version
	Icarus Verilog
$end
$timescale
	1ps
$end
$scope module tb_mux4_1 $end
$var wire 1 ! y $end
$var reg 1 " d0 $end
$var reg 1 # d1 $end
$var reg 1 $ d2 $end
$var reg 1 % d3 $end
$var reg 2 & sel [1:0] $end
$var integer 32 ' i [31:0] $end
$scope module dut $end
$var wire 1 " d0 $end
$var wire 1 # d1 $end
$var wire 1 $ d2 $end
$var wire 1 % d3 $end
$var wire 2 ( sel [1:0] $end
$var wire 1 ) sel_val_0 $end
$var wire 1 * sel_val_1 $end
$var wire 1 + sel_val_2 $end
$var wire 1 , sel_val_3 $end
$var wire 1 ! y $end
$var wire 4 - temp_y [3:0] $end
$scope module mux_d0 $end
$var wire 1 . a $end
$var wire 1 " b $end
$var wire 1 ) sel $end
$var wire 1 / y $end
$upscope $end
$scope module mux_d1 $end
$var wire 1 0 a $end
$var wire 1 # b $end
$var wire 1 * sel $end
$var wire 1 1 y $end
$upscope $end
$scope module mux_d2 $end
$var wire 1 2 a $end
$var wire 1 $ b $end
$var wire 1 + sel $end
$var wire 1 3 y $end
$upscope $end
$upscope $end
$upscope $end
$enddefinitions $end
$comment Show the parameter values. $end
$dumpall
$end
#0
$dumpvars
03
02
01
00
1/
0.
b1 -
0,
0+
0*
1)
b0 (
b0 '
b0 &
0%
0$
0#
1"
1!
$end
#10000
1%
1$
1#
#20000
0!
b0 -
0/
0"
#30000
1!
1/
1.
b11 -
11
0)
1*
0%
0$
1#
b1 &
b1 (
b1 '
#40000
1%
1$
1"
#50000
0%
#60000
1!
1/
10
13
1.
b111 -
11
1+
0*
1$
0#
0"
b10 &
b10 (
b10 '
#70000
1%
1#
1"
#80000
0!
0/
0.
01
00
b0 -
03
0$
#90000
1!
1/
1.
11
10
13
12
b1111 -
0+
1,
1%
0#
0"
b11 &
b11 (
b11 '
#100000
1$
1#
1"
#110000
0!
0/
0.
01
00
03
02
b0 -
0%
0#
#120000
b100 '
