Comparator/comparator_2bit.v
/**
Đầu vào
- A [1:0]
- B [1:0]
Đầu ra 
- A_gt_B = 1 (A>b) 01
- A_eq_B = 1 (A==B) 00
- A_lt_B = 1 (A<B) 10
**/
module comparator_2bit(
    input [1:0] A,
    input [1:0] B,
    output A_gt_B,
    output A_eq_B,
    output A_lt_B

);

    wire eq1,eq0;

    assign eq1 = ~(A[1]^B[1]);
    assign eq0 = ~(A[0]^B[0]);


    //A>B
    assign A_gt_B = (A[1] & ~B[1]) | (eq1 & A[0] & ~B[0]);

    //A<B
    assign A_lt_B = (B[1] & ~A[1]) | (eq1 & B[0] & ~A[0]);

    //A=B
    assign A_eq_B = ~(A[1] ^ B[1]) & ~(A[0] ^ B[0]);

endmodule

Comparator/tb_comparator_2bit.v
`include "comparator_2bit.v"
`timescale 1ns/1ps

module tb_comparator_2bit;

    reg [1:0] A;
    reg [1:0] B;
    wire A_gt_B;
    wire A_eq_B;
    wire A_lt_B;

    comparator_2bit uut(
        .A(A),
        .B(B),
        .A_gt_B(A_gt_B),
        .A_eq_B(A_eq_B),
        .A_lt_B(A_lt_B)
    );

    integer i,j;

    initial begin
        $dumpfile("tb_comparator_2bit.vcd");
        $dumpvars(0,tb_comparator_2bit);
    end

    initial begin
        $display("Time | A  | B  | A_gt_B | A_eq_B | A_lt_B");
        $display("-----+----+----+--------+--------+--------");

        for(i=0; i<4; i=i+1) begin
            for(j=0; j<4; j=j+1) begin
                A = i[1:0];
                B = j[1:0];
                #10; // Wait 10ns for output to settle
                $display("%4dns | %2b | %2b |   %b    |   %b    |   %b", $time, A, B, A_gt_B, A_eq_B, A_lt_B);
            end
        
        end

        $finish;
    end

endmodule

Comparator/tb_comparator_2bit.vcd
$date
	Sat Jul 12 21:06:42 2025
$end
$version
	Icarus Verilog
$end
$timescale
	1ps
$end
$scope module tb_comparator_2bit $end
$var wire 1 ! A_lt_B $end
$var wire 1 " A_gt_B $end
$var wire 1 # A_eq_B $end
$var reg 2 $ A [1:0] $end
$var reg 2 % B [1:0] $end
$var integer 32 & i [31:0] $end
$var integer 32 ' j [31:0] $end
$scope module uut $end
$var wire 2 ( A [1:0] $end
$var wire 1 # A_eq_B $end
$var wire 1 " A_gt_B $end
$var wire 1 ! A_lt_B $end
$var wire 2 ) B [1:0] $end
$var wire 1 * eq0 $end
$var wire 1 + eq1 $end
$upscope $end
$upscope $end
$enddefinitions $end
$comment Show the parameter values. $end
$dumpall
$end
#0
$dumpvars
1+
1*
b0 )
b0 (
b0 '
b0 &
b0 %
b0 $
1#
0"
0!
$end
#10000
1!
0#
0*
b1 %
b1 )
b1 '
#20000
0+
1*
b10 %
b10 )
b10 '
#30000
0*
b11 %
b11 )
b11 '
#40000
1"
1+
0!
b0 %
b0 )
b1 $
b1 (
b1 &
b0 '
#50000
0"
1#
1*
b1 %
b1 )
b1 '
#60000
0"
0#
0+
0*
1!
b10 %
b10 )
b10 '
#70000
1*
b11 %
b11 )
b11 '
#80000
1"
0!
b0 %
b0 )
b10 $
b10 (
b10 &
b0 '
#90000
0*
b1 %
b1 )
b1 '
#100000
0"
1#
1+
1*
b10 %
b10 )
b10 '
#110000
1!
0#
0*
b11 %
b11 )
b11 '
#120000
1"
0!
0+
b0 %
b0 )
b11 $
b11 (
b11 &
b0 '
#130000
1*
b1 %
b1 )
b1 '
#140000
1"
1+
0*
b10 %
b10 )
b10 '
#150000
0"
1#
1*
b11 %
b11 )
b11 '
#160000
b100 &
b100 '
